setup.py
digAgeExtractor/__init__.py
digAgeExtractor/age_helper.py
digAgeExtractor.egg-info/PKG-INFO
digAgeExtractor.egg-info/SOURCES.txt
digAgeExtractor.egg-info/dependency_links.txt
digAgeExtractor.egg-info/requires.txt
digAgeExtractor.egg-info/top_level.txt
test/__init__.py
test/test_age_extractor.py