Metadata-Version: 1.1
Name: digAgeExtractor
Version: 0.3.0
Summary: digAgeExtractor
Home-page: https://github.com/usc-isi-i2/dig-age-extractor
Author: Lingzhe Teng
Author-email: zwein27@gmail.com
License: UNKNOWN
Download-URL: https://github.com/usc-isi-i2/dig-age-extractor
Keywords: age,extractor
Platform: UNKNOWN
